bpp
celeryui
create_test_db
django_bpp
egeria
eksport_pbn
integration_tests
integrator2
miniblog
notifications
nowe_raporty
