Metadata-Version: 2.0
Name: django-bpp
Version: 1.0.1
Summary: System informatyczny do zarządzania bibliografią publikacji pracowników naukowych
Home-page: https://github.com/mpasternak/django-bpp
Author: Michał Pasternak
Author-email: michal.dtz@gmail.com
License: MIT license
Keywords: django_bpp
Platform: UNKNOWN
Classifier: Development Status :: 5 - Production/Stable
Classifier: Intended Audience :: Developers
Classifier: Intended Audience :: Science/Research
Classifier: Intended Audience :: Education
Classifier: Intended Audience :: Healthcare Industry
Classifier: Intended Audience :: Information Technology
Classifier: License :: OSI Approved :: MIT License
Classifier: Natural Language :: Polish
Classifier: Programming Language :: Python :: 3.6
Classifier: Programming Language :: JavaScript
Classifier: Programming Language :: PL/SQL
Requires-Python: >=3.6,<4
Requires-Dist: Django (==1.11.8)
Requires-Dist: psycopg2 (==2.7.1)
Requires-Dist: django-flexible-reports (==0.2.3)
Requires-Dist: django-group-by (==0.3.1)
Requires-Dist: django-columns (==0.1.0)
Requires-Dist: tablib (==0.11.5)
Requires-Dist: django-dirtyfields (==1.2.1)
Requires-Dist: django-messages-extends (==0.5)
Requires-Dist: django-autoslug (==1.9.3)
Requires-Dist: django-autocomplete-light (==3.2.10)
Requires-Dist: django-admin-tools (==0.8.1)
Requires-Dist: xlrd (==0.9.3)
Requires-Dist: celery (==4.0.2)
Requires-Dist: django-tables2 (==1.16.0)
Requires-Dist: django-sendfile (==0.3.11)
Requires-Dist: unidecode (==0.4.20)
Requires-Dist: django-cookie-law (==1.0.13)
Requires-Dist: pyoai (==2.5.0)
Requires-Dist: moai (==2.0.0)
Requires-Dist: django-crispy-forms (==1.6.1)
Requires-Dist: crispy-forms-foundation (==0.3.5)
Requires-Dist: django-compressor (==2.1.1)
Requires-Dist: uwsgi (==2.0.15)
Requires-Dist: zope.interface (==4.1.1)
Requires-Dist: zope.component (==4.1.0)
Requires-Dist: raven (==6.2.1)
Requires-Dist: django-secure-input (==0.9.3)
Requires-Dist: bleach (==2.1.2)
Requires-Dist: django-session-security (==2.5.1)
Requires-Dist: django-password-policies-iplweb (==0.4.4b0)
Requires-Dist: dj-pagination (==2.2.1)
Requires-Dist: requests (==2.18.4)
Requires-Dist: pytz (==2017.3)
Requires-Dist: django-extensions (==1.7.9)
Requires-Dist: django-htmlmin (==0.10.0)
Requires-Dist: Pillow (==4.0.0)
Requires-Dist: olefile (==0.44)
Requires-Dist: django-grappelli (==2.9.1)
Requires-Dist: django-multiseek (==0.9.30)
Requires-Dist: djorm-ext-filtered-contenttypes (==0.4.1)
Requires-Dist: django-braces (==1.8.1)
Requires-Dist: django-loginas (==0.3.2)
Requires-Dist: django-robots (==3.0)
Requires-Dist: django-webmaster-verification (==0.3.0)
Requires-Dist: django-favicon-plus (==0.0.7)
Requires-Dist: dogslow (==1.0.0)
Requires-Dist: django-querysetsequence (==0.8)
Requires-Dist: pypandoc (==1.4)
Requires-Dist: python-memcached (==1.57)
Requires-Dist: django-static-sitemaps (==4.3.0)
Requires-Dist: django-model-utils (==3.0.0)
Requires-Dist: django-jsonview (==1.1.0)
